ommlds/nanochat/rustbpe.cpython-313-darwin.so
ommlds_rs-0.0.0.dev516.dist-info/licenses/LICENSE
ommlds_rs-0.0.0.dev516.dist-info/METADATA
ommlds_rs-0.0.0.dev516.dist-info/WHEEL
ommlds_rs-0.0.0.dev516.dist-info/top_level.txt
ommlds_rs-0.0.0.dev516.dist-info/RECORD
