Metadata-Version: 2.4
Name: ommlds-rs
Version: 0.0.0.dev516
Summary: ommlds
Author: wrmsr
License-Expression: BSD-3-Clause
Project-URL: source, https://github.com/wrmsr/omlish
Classifier: Development Status :: 2 - Pre-Alpha
Classifier: Intended Audience :: Developers
Classifier: Operating System :: OS Independent
Classifier: Operating System :: POSIX
Classifier: Programming Language :: Python :: 3
Classifier: Programming Language :: Python :: 3.13
Requires-Python: >=3.13
License-File: LICENSE
Requires-Dist: ommlds==0.0.0.dev516
Dynamic: license-file
